mispsight/__init__.py
mispsight/conf_sample.py
mispsight/config.py
mispsight/monitoring.py
mispsight/publish.py
mispsight-1.1.0.dist-info/METADATA
mispsight-1.1.0.dist-info/WHEEL
mispsight-1.1.0.dist-info/entry_points.txt
mispsight-1.1.0.dist-info/licenses/COPYING
mispsight-1.1.0.dist-info/RECORD
